odoo/addons/edi_sale_ubl_input_oca/README.rst
odoo/addons/edi_sale_ubl_input_oca/__init__.py
odoo/addons/edi_sale_ubl_input_oca/__manifest__.py
odoo/addons/edi_sale_ubl_input_oca/demo/edi_exchange_type.xml
odoo/addons/edi_sale_ubl_input_oca/i18n/edi_sale_ubl_input_oca.pot
odoo/addons/edi_sale_ubl_input_oca/readme/CONTRIBUTORS.rst
odoo/addons/edi_sale_ubl_input_oca/readme/DESCRIPTION.rst
odoo/addons/edi_sale_ubl_input_oca/static/description/icon.png
odoo/addons/edi_sale_ubl_input_oca/static/description/index.html
odoo/addons/edi_sale_ubl_input_oca/tests/__init__.py
odoo/addons/edi_sale_ubl_input_oca/tests/test_order_in.py
odoo/addons/edi_sale_ubl_input_oca/tests/test_order_in_full_flow.py
odoo14_addon_edi_sale_ubl_input_oca-14.0.1.1.0.dist-info/METADATA
odoo14_addon_edi_sale_ubl_input_oca-14.0.1.1.0.dist-info/WHEEL
odoo14_addon_edi_sale_ubl_input_oca-14.0.1.1.0.dist-info/top_level.txt
odoo14_addon_edi_sale_ubl_input_oca-14.0.1.1.0.dist-info/RECORD
