Metadata-Version: 2.1
Name: odoo14-addon-edi_sale_ubl_input_oca
Version: 14.0.1.1.0
Summary: Configuration and special behaviors for EDI on sales.
Home-page: https://github.com/OCA/edi
Author: Camptocamp,Odoo Community Association (OCA)
Author-email: support@odoo-community.org
License: AGPL-3
Classifier: Programming Language :: Python
Classifier: Framework :: Odoo
Classifier: Framework :: Odoo :: 14.0
Classifier: License :: OSI Approved :: GNU Affero General Public License v3
Classifier: Development Status :: 3 - Alpha
Requires-Python: >=3.6
Requires-Dist: odoo14-addon-edi-sale-input-oca
Requires-Dist: odoo14-addon-edi-sale-ubl-oca
Requires-Dist: odoo14-addon-edi-ubl-oca
Requires-Dist: odoo14-addon-edi-xml-oca
Requires-Dist: odoo14-addon-sale-order-import-ubl
Requires-Dist: odoo<14.1dev,>=14.0a
